truverifi/VERSION
truverifi/__attr__.py
truverifi/__init__.py
truverifi/_compat.py
truverifi/exception.py
truverifi/truverifi.py
truverifi-0.1.0.dist-info/AUTHORS.md
truverifi-0.1.0.dist-info/LICENSE
truverifi-0.1.0.dist-info/METADATA
truverifi-0.1.0.dist-info/WHEEL
truverifi-0.1.0.dist-info/top_level.txt
truverifi-0.1.0.dist-info/RECORD
