Metadata-Version: 2.1
Name: truverifi
Version: 0.1.0
Summary: Python client library for truverifi
Home-page: https://github.com/achillesrasquinha/truverifi
Author: Achilles Rasquinha
Author-email: achillesrasquinha@gmail.com
License: MIT License
Keywords: python client library for truverifi
Platform: UNKNOWN
Classifier: Development Status :: 5 - Production/Stable
Classifier: Environment :: Console
Classifier: Intended Audience :: Developers
Classifier: License :: OSI Approved :: MIT License
Classifier: Programming Language :: Python :: 3
Classifier: Programming Language :: Python :: 3.4
Classifier: Programming Language :: Python :: 3.5
Classifier: Programming Language :: Python :: 3.6
Classifier: Programming Language :: Python :: 3.7
Classifier: Programming Language :: Python :: Implementation :: CPython
Classifier: Programming Language :: Python :: Implementation :: PyPy
Requires-Dist: requests
Provides-Extra: dev
Requires-Dist: ipython ; extra == 'dev'
Requires-Dist: bumpversion ; extra == 'dev'
Requires-Dist: twine ; extra == 'dev'
Requires-Dist: sphinx ; extra == 'dev'
Requires-Dist: recommonmark ; extra == 'dev'
Requires-Dist: pylint ; extra == 'dev'
Requires-Dist: autopep8 ; extra == 'dev'
Requires-Dist: requests ; extra == 'dev'
Requires-Dist: pytest ; extra == 'dev'
Requires-Dist: pytest-cov ; extra == 'dev'
Requires-Dist: pytest-xdist ; extra == 'dev'
Requires-Dist: pytest-sugar ; extra == 'dev'
Requires-Dist: pytest-travis-fold ; extra == 'dev'
Requires-Dist: detox ; extra == 'dev'
Requires-Dist: tox-travis ; extra == 'dev'
Requires-Dist: coveralls ; extra == 'dev'
